MANIFEST.in
README.md
requirements.txt
setup.cfg
setup.py
tradingtime/__init__.py
tradingtime/future.py
tradingtime/futures_exch.json
tradingtime/futures_holiday.json
tradingtime/futures_tradingtime.json
tradingtime/test.json
tradingtime.egg-info/PKG-INFO
tradingtime.egg-info/SOURCES.txt
tradingtime.egg-info/dependency_links.txt
tradingtime.egg-info/requires.txt
tradingtime.egg-info/top_level.txt