Metadata-Version: 1.1
Name: tradingtime
Version: 0.0.7
Summary: 证券市场交易日历 2019.03.26
Home-page: https://github.com/lamter/tradingtime
Author: lamter
Author-email: lamter.fu@gmail.com
License: UNKNOWN
Keywords: tradingtime
Platform: UNKNOWN
Classifier: Programming Language :: Python :: 2.7
Classifier: Programming Language :: Python :: 3.5
Classifier: License :: OSI Approved :: MIT License
